README.md
setup.py
src/vdk/plugin/meta_jobs/cached_data_job_executor.py
src/vdk/plugin/meta_jobs/dag_validator.py
src/vdk/plugin/meta_jobs/dags_plugin.py
src/vdk/plugin/meta_jobs/meta.py
src/vdk/plugin/meta_jobs/meta_configuration.py
src/vdk/plugin/meta_jobs/meta_dag.py
src/vdk/plugin/meta_jobs/meta_job_runner.py
src/vdk/plugin/meta_jobs/remote_data_job.py
src/vdk/plugin/meta_jobs/remote_data_job_executor.py
src/vdk/plugin/meta_jobs/time_based_queue.py
src/vdk/plugin/meta_jobs/api/meta_job.py
src/vdk_meta_jobs.egg-info/PKG-INFO
src/vdk_meta_jobs.egg-info/SOURCES.txt
src/vdk_meta_jobs.egg-info/dependency_links.txt
src/vdk_meta_jobs.egg-info/entry_points.txt
src/vdk_meta_jobs.egg-info/requires.txt
src/vdk_meta_jobs.egg-info/top_level.txt
tests/test_meta_dag.py
tests/test_meta_job.py
tests/test_time_based_queue.py
tests/test_tracking_job_executor.py