Metadata-Version: 2.1
Name: vdk-meta-jobs
Version: 0.1.836044868
Summary: Express dependecies between data jobs.
Home-page: https://github.com/vmware/versatile-data-kit
Classifier: Development Status :: 2 - Pre-Alpha
Classifier: License :: OSI Approved :: Apache Software License
Classifier: Programming Language :: Python :: 3.7
Classifier: Programming Language :: Python :: 3.8
Classifier: Programming Language :: Python :: 3.9
Classifier: Programming Language :: Python :: 3.10
Classifier: Programming Language :: Python :: 3.11
